tsl-0.0.1.dist-info/metadata.json
tsl-0.0.1.dist-info/DESCRIPTION.rst
tsl-0.0.1.dist-info/entry_points.txt
tsl-0.0.1.dist-info/top_level.txt
tsl-0.0.1.dist-info/RECORD
tsl-0.0.1.dist-info/WHEEL
tsl-0.0.1.dist-info/METADATA
trans/util.py
trans/Trans.py
trans/__init__.py
