Metadata-Version: 2.0
Name: tsl
Version: 0.0.1
Summary: 适用于在linux终端通过百度api查询单词或者翻译词句
Home-page: https://github.com/idbord/trans
Author: idbord
Author-email: byzone482@gmail.com
License: MIT
Keywords: tsl,translate,baidu,dict,baidu api
Platform: linux
Classifier: Development Status :: 4 - Beta
Classifier: Intended Audience :: Developers
Classifier: License :: OSI Approved :: MIT License
Classifier: Programming Language :: Python :: 2.7
Classifier: Operating System :: POSIX :: Linux
